{
  "project": "Vibe Product Studio",
  "description": "Tracks product-building and design tool repositories from GitHub signals.",
  "source": {
    "type": "github-search",
    "query": "topic:productivity stars:>50 pushed:>=2024-01-01"
  },
  "total_found": 824,
  "items": [
    {
      "id": 231283452,
      "full_name": "excalidraw/excalidraw",
      "html_url": "https://github.com/excalidraw/excalidraw",
      "description": "Virtual whiteboard for sketching hand-drawn like diagrams",
      "stars": 122477,
      "forks": 13508,
      "language": "TypeScript",
      "pushed_at": "2026-05-04T16:55:40Z",
      "updated_at": "2026-05-04T17:20:51Z"
    },
    {
      "id": 164140756,
      "full_name": "files-community/Files",
      "html_url": "https://github.com/files-community/Files",
      "description": "A modern file manager that helps users organize their files and folders.",
      "stars": 43264,
      "forks": 2705,
      "language": "C#",
      "pushed_at": "2026-05-04T15:43:20Z",
      "updated_at": "2026-05-04T17:23:11Z"
    },
    {
      "id": 78243781,
      "full_name": "super-productivity/super-productivity",
      "html_url": "https://github.com/super-productivity/super-productivity",
      "description": "Super Productivity is an advanced todo list app with integrated Timeboxing and time tracking capabilities. It also comes with integrations for Jira, GitLab, GitHub and Open Project.",
      "stars": 19033,
      "forks": 1651,
      "language": "TypeScript",
      "pushed_at": "2026-05-04T17:12:00Z",
      "updated_at": "2026-05-04T17:18:13Z"
    },
    {
      "id": 205326947,
      "full_name": "espanso/espanso",
      "html_url": "https://github.com/espanso/espanso",
      "description": "A Privacy-first, Cross-platform Text Expander written in Rust",
      "stars": 13743,
      "forks": 406,
      "language": "Rust",
      "pushed_at": "2026-05-04T17:08:01Z",
      "updated_at": "2026-05-04T17:26:14Z"
    },
    {
      "id": 129699403,
      "full_name": "tuist/tuist",
      "html_url": "https://github.com/tuist/tuist",
      "description": "Your platform team, as a service",
      "stars": 5637,
      "forks": 735,
      "language": "Swift",
      "pushed_at": "2026-05-04T17:21:37Z",
      "updated_at": "2026-05-04T14:47:56Z"
    },
    {
      "id": 11512043,
      "full_name": "tasks/tasks",
      "html_url": "https://github.com/tasks/tasks",
      "description": "Bringing Astrid Tasks back from the dead",
      "stars": 5184,
      "forks": 620,
      "language": "Kotlin",
      "pushed_at": "2026-05-04T16:49:24Z",
      "updated_at": "2026-05-04T16:49:30Z"
    },
    {
      "id": 300155217,
      "full_name": "CollaboraOnline/online",
      "html_url": "https://github.com/CollaboraOnline/online",
      "description": "Collabora Online is a collaborative online office suite based on LibreOffice technology. This is also the source for the Collabora Office apps for iOS and Android. ",
      "stars": 3198,
      "forks": 1006,
      "language": "C++",
      "pushed_at": "2026-05-04T15:04:56Z",
      "updated_at": "2026-05-04T15:18:14Z"
    },
    {
      "id": 1114821770,
      "full_name": "DaKheera47/job-ops",
      "html_url": "https://github.com/DaKheera47/job-ops",
      "description": "job-ops: DevOps principles applied to job hunting. A self-hosted pipeline to track, analyze, and assist your application process",
      "stars": 2954,
      "forks": 345,
      "language": "TypeScript",
      "pushed_at": "2026-05-04T14:46:26Z",
      "updated_at": "2026-05-04T15:16:02Z"
    },
    {
      "id": 323279421,
      "full_name": "LinwoodDev/Butterfly",
      "html_url": "https://github.com/LinwoodDev/Butterfly",
      "description": "🎨 Powerful, minimalistic, cross-platform, opensource note-taking app",
      "stars": 1837,
      "forks": 135,
      "language": "Dart",
      "pushed_at": "2026-05-04T15:27:53Z",
      "updated_at": "2026-05-04T15:27:59Z"
    },
    {
      "id": 1085525076,
      "full_name": "steven-jianhao-li/zotero-AI-Butler",
      "html_url": "https://github.com/steven-jianhao-li/zotero-AI-Butler",
      "description": "【Zotero AI 管家】调用大模型，自动精读论文库里的论文，总结为Zotero笔记。支持主流大模型平台！您只需像往常一样把文献丢进 Zotero， 管家会自动帮您精读论文，将文章揉碎了总结为笔记，让您“十分钟完全了解”这篇论文！",
      "stars": 1168,
      "forks": 64,
      "language": "JavaScript",
      "pushed_at": "2026-05-04T17:20:13Z",
      "updated_at": "2026-05-04T16:30:48Z"
    },
    {
      "id": 1111053300,
      "full_name": "yuzeguitarist/Deck",
      "html_url": "https://github.com/yuzeguitarist/Deck",
      "description": "Deck is a modern, native, privacy-first clipboard manager for macOS.",
      "stars": 1138,
      "forks": 31,
      "language": "Swift",
      "pushed_at": "2026-05-04T17:09:40Z",
      "updated_at": "2026-05-04T17:23:26Z"
    },
    {
      "id": 1175857225,
      "full_name": "skalesapp/skales",
      "html_url": "https://github.com/skalesapp/skales",
      "description": "Your local AI Desktop Agent for Windows, macOS & Linux. Agent Skills (SKILL.md), autonomous coding (Codework), multi-agent teams, desktop automation, 15+ AI providers, Desktop Buddy. No Docker, no terminal. Free.",
      "stars": 909,
      "forks": 152,
      "language": "TypeScript",
      "pushed_at": "2026-05-04T16:41:33Z",
      "updated_at": "2026-05-04T16:41:37Z"
    },
    {
      "id": 1111978380,
      "full_name": "dongdongbh/Mindwtr",
      "html_url": "https://github.com/dongdongbh/Mindwtr",
      "description": "A complete Getting Things Done (GTD) productivity system for desktop and mobile.",
      "stars": 798,
      "forks": 46,
      "language": "TypeScript",
      "pushed_at": "2026-05-04T17:14:07Z",
      "updated_at": "2026-05-04T17:14:37Z"
    },
    {
      "id": 1148683593,
      "full_name": "eval-exec/neomacs",
      "html_url": "https://github.com/eval-exec/neomacs",
      "description": "NEO Emacs (WIP): A GPU-powered Emacs written in Rust with a modern display engine.  Aiming for modern design/multi-threaded Elisp, 10x performance and 100% Emacs compatibility. 🚀  Inline 4K images/4K videos/WPEWebKit using GPU acceleration, DMA-BUF, ZERO-COPY. Rich animation effects support.",
      "stars": 695,
      "forks": 25,
      "language": "Emacs Lisp",
      "pushed_at": "2026-05-04T17:21:35Z",
      "updated_at": "2026-05-04T17:21:39Z"
    },
    {
      "id": 1125258937,
      "full_name": "urzeye/ophel",
      "html_url": "https://github.com/urzeye/ophel",
      "description": "Turn AI conversations into organized, reusable workflows — across major AI platforms. | 把 AI 对话转化为可组织、可复用的工作流，适用于主流 AI 平台",
      "stars": 593,
      "forks": 32,
      "language": "TypeScript",
      "pushed_at": "2026-05-04T17:21:06Z",
      "updated_at": "2026-05-04T17:21:09Z"
    }
  ]
}
